frest/__init__.py
frest/app.py
frest/database.py
frest/decorators.py
frest/forms.py
frest/mail.py
frest/utils.py
frest/wsgi.py
frest/auth/__init__.py
frest/auth/forms.py
frest/auth/models.py
frest/auth/routes.py
frest/manage/__init__.py
frest/manage/bcolors.py
frest/manage/utils.py
frest/templates/app.txt
frest/templates/database.txt
frest/templates/form.txt
frest/templates/mail.txt
frest/templates/models.txt
frest/templates/routes.txt
frest/templates/wsgi.txt
frest-0.1.5.post2.data/scripts/frest
frest-0.1.5.post2.dist-info/LICENSE
frest-0.1.5.post2.dist-info/METADATA
frest-0.1.5.post2.dist-info/WHEEL
frest-0.1.5.post2.dist-info/top_level.txt
frest-0.1.5.post2.dist-info/RECORD
